<?xml version="1.0" encoding="UTF-8"?>
<entity-engine-xml>
    <!-- Organigramma Ospedale Cardarelli - Dipartimenti e UOC -->
    
    <!-- COLLEGAMENTI ALLA RADICE ORGANIZZATIVA -->
    <!-- Questi collegamenti sono necessari per visualizzare l'organigramma nella pagina web -->
    
    <!-- Collegamento Dipartimenti alla radice Company -->
    <PartyRelationship partyIdFrom="Company" partyIdTo="DEPT_CAR_TOR" roleTypeIdFrom="INTERNAL_ORGANIZATIO" roleTypeIdTo="INTERNAL_ORGANIZATIO" partyRelationshipTypeId="GROUP_ROLLUP" fromDate="2024-01-01 00:00:00"/>
    <PartyRelationship partyIdFrom="Company" partyIdTo="DEPT_CHIRURGICO" roleTypeIdFrom="INTERNAL_ORGANIZATIO" roleTypeIdTo="INTERNAL_ORGANIZATIO" partyRelationshipTypeId="GROUP_ROLLUP" fromDate="2024-01-01 00:00:00"/>
    <PartyRelationship partyIdFrom="Company" partyIdTo="DEPT_MEDICINA_INT" roleTypeIdFrom="INTERNAL_ORGANIZATIO" roleTypeIdTo="INTERNAL_ORGANIZATIO" partyRelationshipTypeId="GROUP_ROLLUP" fromDate="2024-01-01 00:00:00"/>
    <PartyRelationship partyIdFrom="Company" partyIdTo="DEPT_DIAGNOSTICA" roleTypeIdFrom="INTERNAL_ORGANIZATIO" roleTypeIdTo="INTERNAL_ORGANIZATIO" partyRelationshipTypeId="GROUP_ROLLUP" fromDate="2024-01-01 00:00:00"/>
    <PartyRelationship partyIdFrom="Company" partyIdTo="DEPT_TERAPIE_INT" roleTypeIdFrom="INTERNAL_ORGANIZATIO" roleTypeIdTo="INTERNAL_ORGANIZATIO" partyRelationshipTypeId="GROUP_ROLLUP" fromDate="2024-01-01 00:00:00"/>
    <PartyRelationship partyIdFrom="Company" partyIdTo="DEPT_AMMINISTRATIVO" roleTypeIdFrom="INTERNAL_ORGANIZATIO" roleTypeIdTo="INTERNAL_ORGANIZATIO" partyRelationshipTypeId="GROUP_ROLLUP" fromDate="2024-01-01 00:00:00"/>
    
    <!-- DIPARTIMENTI PRINCIPALI -->
    
    <!-- Dipartimento Cardio-Toraco-Vascolare -->
    <Party partyId="DEPT_CAR_TOR" partyTypeId="PARTY_GROUP" statusId="PARTY_ENABLED" createdDate="2024-01-01 00:00:00" lastModifiedDate="2024-01-01 00:00:00"/>
    <PartyGroup partyId="DEPT_CAR_TOR" groupName="Dipartimento Cardio-Toraco-Vascolare" groupNameLocal="Dipartimento Cardio-Toraco-Vascolare" partyTypeId="PARTY_GROUP" />
    <PartyRole partyId="DEPT_CAR_TOR" roleTypeId="INTERNAL_ORGANIZATIO" fromDate="2024-01-01 00:00:00"/>
    
    <!-- Dipartimento Chirurgico -->
    <Party partyId="DEPT_CHIRURGICO" partyTypeId="PARTY_GROUP" statusId="PARTY_ENABLED" createdDate="2024-01-01 00:00:00" lastModifiedDate="2024-01-01 00:00:00"/>
    <PartyGroup partyId="DEPT_CHIRURGICO" groupName="Dipartimento Chirurgico" groupNameLocal="Dipartimento Chirurgico" partyTypeId="PARTY_GROUP" />
    <PartyRole partyId="DEPT_CHIRURGICO" roleTypeId="INTERNAL_ORGANIZATIO" fromDate="2024-01-01 00:00:00"/>
    
    <!-- Dipartimento Medicina Interna -->
    <Party partyId="DEPT_MEDICINA_INT" partyTypeId="PARTY_GROUP" statusId="PARTY_ENABLED" createdDate="2024-01-01 00:00:00" lastModifiedDate="2024-01-01 00:00:00"/>
    <PartyGroup partyId="DEPT_MEDICINA_INT" groupName="Dipartimento Medicina Interna" groupNameLocal="Dipartimento Medicina Interna" partyTypeId="PARTY_GROUP" />
    <PartyRole partyId="DEPT_MEDICINA_INT" roleTypeId="INTERNAL_ORGANIZATIO" fromDate="2024-01-01 00:00:00"/>
    
    <!-- Dipartimento Diagnostica -->
    <Party partyId="DEPT_DIAGNOSTICA" partyTypeId="PARTY_GROUP" statusId="PARTY_ENABLED" createdDate="2024-01-01 00:00:00" lastModifiedDate="2024-01-01 00:00:00"/>
    <PartyGroup partyId="DEPT_DIAGNOSTICA" groupName="Dipartimento Diagnostica" groupNameLocal="Dipartimento Diagnostica" partyTypeId="PARTY_GROUP" />
    <PartyRole partyId="DEPT_DIAGNOSTICA" roleTypeId="INTERNAL_ORGANIZATIO" fromDate="2024-01-01 00:00:00"/>
    
    <!-- Dipartimento Terapie Intensive -->
    <Party partyId="DEPT_TERAPIE_INT" partyTypeId="PARTY_GROUP" statusId="PARTY_ENABLED" createdDate="2024-01-01 00:00:00" lastModifiedDate="2024-01-01 00:00:00"/>
    <PartyGroup partyId="DEPT_TERAPIE_INT" groupName="Dipartimento Terapie Intensive" groupNameLocal="Dipartimento Terapie Intensive" partyTypeId="PARTY_GROUP" />
    <PartyRole partyId="DEPT_TERAPIE_INT" roleTypeId="INTERNAL_ORGANIZATIO" fromDate="2024-01-01 00:00:00"/>
    
    <!-- Dipartimento Servizi Amministrativi -->
    <Party partyId="DEPT_AMMINISTRATIVO" partyTypeId="PARTY_GROUP" statusId="PARTY_ENABLED" createdDate="2024-01-01 00:00:00" lastModifiedDate="2024-01-01 00:00:00"/>
    <PartyGroup partyId="DEPT_AMMINISTRATIVO" groupName="Dipartimento Servizi Amministrativi" groupNameLocal="Dipartimento Servizi Amministrativi" partyTypeId="PARTY_GROUP" />
    <PartyRole partyId="DEPT_AMMINISTRATIVO" roleTypeId="INTERNAL_ORGANIZATIO" fromDate="2024-01-01 00:00:00"/>
    
    <!-- UOC DEL DIPARTIMENTO CARDIO-TORACO-VASCOLARE -->
    
    <!-- UOC Cardiologia -->
    <Party partyId="UOC_CARDIOLOGIA" partyTypeId="PARTY_GROUP" statusId="PARTY_ENABLED" createdDate="2024-01-01 00:00:00" lastModifiedDate="2024-01-01 00:00:00"/>
    <PartyGroup partyId="UOC_CARDIOLOGIA" groupName="UOC Cardiologia" groupNameLocal="UOC Cardiologia" partyTypeId="PARTY_GROUP" />
    <PartyRole partyId="UOC_CARDIOLOGIA" roleTypeId="ORGANIZATION_UNIT" fromDate="2024-01-01 00:00:00"/>
    <PartyRelationship partyIdFrom="DEPT_CAR_TOR" partyIdTo="UOC_CARDIOLOGIA" roleTypeIdFrom="INTERNAL_ORGANIZATIO" roleTypeIdTo="ORGANIZATION_UNIT" partyRelationshipTypeId="GROUP_ROLLUP" fromDate="2024-01-01 00:00:00"/>
    
    <!-- UOC Cardiologia con UTIC -->
    <Party partyId="UOC_CARDIOLOGIA_UTIC" partyTypeId="PARTY_GROUP" statusId="PARTY_ENABLED" createdDate="2024-01-01 00:00:00" lastModifiedDate="2024-01-01 00:00:00"/>
    <PartyGroup partyId="UOC_CARDIOLOGIA_UTIC" groupName="UOC Cardiologia con UTIC" groupNameLocal="UOC Cardiologia con UTIC" partyTypeId="PARTY_GROUP" />
    <PartyRole partyId="UOC_CARDIOLOGIA_UTIC" roleTypeId="INTERNAL_ORGANIZATIO" fromDate="2024-01-01 00:00:00"/>
    <PartyRelationship partyIdFrom="DEPT_CAR_TOR" partyIdTo="UOC_CARDIOLOGIA_UTIC" roleTypeIdFrom="INTERNAL_ORGANIZATIO" roleTypeIdTo="INTERNAL_ORGANIZATIO" partyRelationshipTypeId="GROUP_ROLLUP" fromDate="2024-01-01 00:00:00"/>
    
    <!-- UOC Chirurgia Toracica -->
    <Party partyId="UOC_CHIR_TORACICA" partyTypeId="PARTY_GROUP" statusId="PARTY_ENABLED" createdDate="2024-01-01 00:00:00" lastModifiedDate="2024-01-01 00:00:00"/>
    <PartyGroup partyId="UOC_CHIR_TORACICA" groupName="UOC Chirurgia Toracica" groupNameLocal="UOC Chirurgia Toracica" partyTypeId="PARTY_GROUP" />
    <PartyRole partyId="UOC_CHIR_TORACICA" roleTypeId="INTERNAL_ORGANIZATIO" fromDate="2024-01-01 00:00:00"/>
    <PartyRelationship partyIdFrom="DEPT_CAR_TOR" partyIdTo="UOC_CHIR_TORACICA" roleTypeIdFrom="INTERNAL_ORGANIZATIO" roleTypeIdTo="INTERNAL_ORGANIZATIO" partyRelationshipTypeId="GROUP_ROLLUP" fromDate="2024-01-01 00:00:00"/>
    
    <!-- UOC Chirurgia Vascolare ed Endovascolare -->
    <Party partyId="UOC_CHIR_VASCOLARE" partyTypeId="PARTY_GROUP" statusId="PARTY_ENABLED" createdDate="2024-01-01 00:00:00" lastModifiedDate="2024-01-01 00:00:00"/>
    <PartyGroup partyId="UOC_CHIR_VASCOLARE" groupName="UOC Chirurgia Vascolare ed Endovascolare" groupNameLocal="UOC Chirurgia Vascolare ed Endovascolare" partyTypeId="PARTY_GROUP" />
    <PartyRole partyId="UOC_CHIR_VASCOLARE" roleTypeId="INTERNAL_ORGANIZATIO" fromDate="2024-01-01 00:00:00"/>
    <PartyRelationship partyIdFrom="DEPT_CAR_TOR" partyIdTo="UOC_CHIR_VASCOLARE" roleTypeIdFrom="INTERNAL_ORGANIZATIO" roleTypeIdTo="INTERNAL_ORGANIZATIO" partyRelationshipTypeId="GROUP_ROLLUP" fromDate="2024-01-01 00:00:00"/>
    
    <!-- UOC DEL DIPARTIMENTO CHIRURGICO -->
    
    <!-- UOC Chirurgia Generale ad alta specializzazione gastroenterologica -->
    <Party partyId="UOC_CHIR_GASTRO" partyTypeId="PARTY_GROUP" statusId="PARTY_ENABLED" createdDate="2024-01-01 00:00:00" lastModifiedDate="2024-01-01 00:00:00"/>
    <PartyGroup partyId="UOC_CHIR_GASTRO" groupName="UOC Chirurgia Generale ad alta specializzazione gastroenterologica" groupNameLocal="UOC Chirurgia Generale ad alta specializzazione gastroenterologica" partyTypeId="PARTY_GROUP" />
    <PartyRole partyId="UOC_CHIR_GASTRO" roleTypeId="INTERNAL_ORGANIZATIO" fromDate="2024-01-01 00:00:00"/>
    <PartyRelationship partyIdFrom="DEPT_CHIRURGICO" partyIdTo="UOC_CHIR_GASTRO" roleTypeIdFrom="INTERNAL_ORGANIZATIO" roleTypeIdTo="INTERNAL_ORGANIZATIO" partyRelationshipTypeId="GROUP_ROLLUP" fromDate="2024-01-01 00:00:00"/>
    
    <!-- UOC Chirurgia Epatobiliare e Trapianto di Fegato -->
    <Party partyId="UOC_CHIR_EPATICA" partyTypeId="PARTY_GROUP" statusId="PARTY_ENABLED" createdDate="2024-01-01 00:00:00" lastModifiedDate="2024-01-01 00:00:00"/>
    <PartyGroup partyId="UOC_CHIR_EPATICA" groupName="UOC Chirurgia Epatobiliare e Trapianto di Fegato" groupNameLocal="UOC Chirurgia Epatobiliare e Trapianto di Fegato" partyTypeId="PARTY_GROUP" />
    <PartyRole partyId="UOC_CHIR_EPATICA" roleTypeId="INTERNAL_ORGANIZATIO" fromDate="2024-01-01 00:00:00"/>
    <PartyRelationship partyIdFrom="DEPT_CHIRURGICO" partyIdTo="UOC_CHIR_EPATICA" roleTypeIdFrom="INTERNAL_ORGANIZATIO" roleTypeIdTo="INTERNAL_ORGANIZATIO" partyRelationshipTypeId="GROUP_ROLLUP" fromDate="2024-01-01 00:00:00"/>
    
    <!-- UOC Chirurgia Maxillo-Facciale -->
    <Party partyId="UOC_CHIR_MAXFAC" partyTypeId="PARTY_GROUP" statusId="PARTY_ENABLED" createdDate="2024-01-01 00:00:00" lastModifiedDate="2024-01-01 00:00:00"/>
    <PartyGroup partyId="UOC_CHIR_MAXFAC" groupName="UOC Chirurgia Maxillo-Facciale" groupNameLocal="UOC Chirurgia Maxillo-Facciale" partyTypeId="PARTY_GROUP" />
    <PartyRole partyId="UOC_CHIR_MAXFAC" roleTypeId="INTERNAL_ORGANIZATIO" fromDate="2024-01-01 00:00:00"/>
    <PartyRelationship partyIdFrom="DEPT_CHIRURGICO" partyIdTo="UOC_CHIR_MAXFAC" roleTypeIdFrom="INTERNAL_ORGANIZATIO" roleTypeIdTo="INTERNAL_ORGANIZATIO" partyRelationshipTypeId="GROUP_ROLLUP" fromDate="2024-01-01 00:00:00"/>
    
    <!-- UOC Ortopedia 1 -->
    <Party partyId="UOC_ORTOPEDIA_1" partyTypeId="PARTY_GROUP" statusId="PARTY_ENABLED" createdDate="2024-01-01 00:00:00" lastModifiedDate="2024-01-01 00:00:00"/>
    <PartyGroup partyId="UOC_ORTOPEDIA_1" groupName="UOC Ortopedia 1" groupNameLocal="UOC Ortopedia 1" partyTypeId="PARTY_GROUP" />
    <PartyRole partyId="UOC_ORTOPEDIA_1" roleTypeId="INTERNAL_ORGANIZATIO" fromDate="2024-01-01 00:00:00"/>
    <PartyRelationship partyIdFrom="DEPT_CHIRURGICO" partyIdTo="UOC_ORTOPEDIA_1" roleTypeIdFrom="INTERNAL_ORGANIZATIO" roleTypeIdTo="INTERNAL_ORGANIZATIO" partyRelationshipTypeId="GROUP_ROLLUP" fromDate="2024-01-01 00:00:00"/>
    
    <!-- UOC Ortopedia 2 -->
    <Party partyId="UOC_ORTOPEDIA_2" partyTypeId="PARTY_GROUP" statusId="PARTY_ENABLED" createdDate="2024-01-01 00:00:00" lastModifiedDate="2024-01-01 00:00:00"/>
    <PartyGroup partyId="UOC_ORTOPEDIA_2" groupName="UOC Ortopedia 2" groupNameLocal="UOC Ortopedia 2" partyTypeId="PARTY_GROUP" />
    <PartyRole partyId="UOC_ORTOPEDIA_2" roleTypeId="INTERNAL_ORGANIZATIO" fromDate="2024-01-01 00:00:00"/>
    <PartyRelationship partyIdFrom="DEPT_CHIRURGICO" partyIdTo="UOC_ORTOPEDIA_2" roleTypeIdFrom="INTERNAL_ORGANIZATIO" roleTypeIdTo="INTERNAL_ORGANIZATIO" partyRelationshipTypeId="GROUP_ROLLUP" fromDate="2024-01-01 00:00:00"/>
    
    <!-- UOC Neurochirurgia -->
    <Party partyId="UOC_NEUROCHIRURGIA" partyTypeId="PARTY_GROUP" statusId="PARTY_ENABLED" createdDate="2024-01-01 00:00:00" lastModifiedDate="2024-01-01 00:00:00"/>
    <PartyGroup partyId="UOC_NEUROCHIRURGIA" groupName="UOC Neurochirurgia" groupNameLocal="UOC Neurochirurgia" partyTypeId="PARTY_GROUP" />
    <PartyRole partyId="UOC_NEUROCHIRURGIA" roleTypeId="INTERNAL_ORGANIZATIO" fromDate="2024-01-01 00:00:00"/>
    <PartyRelationship partyIdFrom="DEPT_CHIRURGICO" partyIdTo="UOC_NEUROCHIRURGIA" roleTypeIdFrom="INTERNAL_ORGANIZATIO" roleTypeIdTo="INTERNAL_ORGANIZATIO" partyRelationshipTypeId="GROUP_ROLLUP" fromDate="2024-01-01 00:00:00"/>
    
    <!-- UOC Urologia -->
    <Party partyId="UOC_UROLOGIA" partyTypeId="PARTY_GROUP" statusId="PARTY_ENABLED" createdDate="2024-01-01 00:00:00" lastModifiedDate="2024-01-01 00:00:00"/>
    <PartyGroup partyId="UOC_UROLOGIA" groupName="UOC Urologia" groupNameLocal="UOC Urologia" partyTypeId="PARTY_GROUP" />
    <PartyRole partyId="UOC_UROLOGIA" roleTypeId="INTERNAL_ORGANIZATIO" fromDate="2024-01-01 00:00:00"/>
    <PartyRelationship partyIdFrom="DEPT_CHIRURGICO" partyIdTo="UOC_UROLOGIA" roleTypeIdFrom="INTERNAL_ORGANIZATIO" roleTypeIdTo="INTERNAL_ORGANIZATIO" partyRelationshipTypeId="GROUP_ROLLUP" fromDate="2024-01-01 00:00:00"/>
    
    <!-- UOC DEL DIPARTIMENTO MEDICINA INTERNA -->
    
    <!-- UOC Medicina Interna 1 -->
    <Party partyId="UOC_MEDICINA_INT_1" partyTypeId="PARTY_GROUP" statusId="PARTY_ENABLED" createdDate="2024-01-01 00:00:00" lastModifiedDate="2024-01-01 00:00:00"/>
    <PartyGroup partyId="UOC_MEDICINA_INT_1" groupName="UOC Medicina Interna 1" groupNameLocal="UOC Medicina Interna 1" partyTypeId="PARTY_GROUP" />
    <PartyRole partyId="UOC_MEDICINA_INT_1" roleTypeId="INTERNAL_ORGANIZATIO" fromDate="2024-01-01 00:00:00"/>
    <PartyRelationship partyIdFrom="DEPT_MEDICINA_INT" partyIdTo="UOC_MEDICINA_INT_1" roleTypeIdFrom="INTERNAL_ORGANIZATIO" roleTypeIdTo="INTERNAL_ORGANIZATIO" partyRelationshipTypeId="GROUP_ROLLUP" fromDate="2024-01-01 00:00:00"/>
    
    <!-- UOC Medicina Interna 2 -->
    <Party partyId="UOC_MEDICINA_INT_2" partyTypeId="PARTY_GROUP" statusId="PARTY_ENABLED" createdDate="2024-01-01 00:00:00" lastModifiedDate="2024-01-01 00:00:00"/>
    <PartyGroup partyId="UOC_MEDICINA_INT_2" groupName="UOC Medicina Interna 2" groupNameLocal="UOC Medicina Interna 2" partyTypeId="PARTY_GROUP" />
    <PartyRole partyId="UOC_MEDICINA_INT_2" roleTypeId="INTERNAL_ORGANIZATIO" fromDate="2024-01-01 00:00:00"/>
    <PartyRelationship partyIdFrom="DEPT_MEDICINA_INT" partyIdTo="UOC_MEDICINA_INT_2" roleTypeIdFrom="INTERNAL_ORGANIZATIO" roleTypeIdTo="INTERNAL_ORGANIZATIO" partyRelationshipTypeId="GROUP_ROLLUP" fromDate="2024-01-01 00:00:00"/>
    
    <!-- UOC Medicina Interna 3 -->
    <Party partyId="UOC_MEDICINA_INT_3" partyTypeId="PARTY_GROUP" statusId="PARTY_ENABLED" createdDate="2024-01-01 00:00:00" lastModifiedDate="2024-01-01 00:00:00"/>
    <PartyGroup partyId="UOC_MEDICINA_INT_3" groupName="UOC Medicina Interna 3" groupNameLocal="UOC Medicina Interna 3" partyTypeId="PARTY_GROUP" />
    <PartyRole partyId="UOC_MEDICINA_INT_3" roleTypeId="INTERNAL_ORGANIZATIO" fromDate="2024-01-01 00:00:00"/>
    <PartyRelationship partyIdFrom="DEPT_MEDICINA_INT" partyIdTo="UOC_MEDICINA_INT_3" roleTypeIdFrom="INTERNAL_ORGANIZATIO" roleTypeIdTo="INTERNAL_ORGANIZATIO" partyRelationshipTypeId="GROUP_ROLLUP" fromDate="2024-01-01 00:00:00"/>
    
    <!-- UOC Medicina DEA e Complessità Clinica -->
    <Party partyId="UOC_MEDICINA_DEA" partyTypeId="PARTY_GROUP" statusId="PARTY_ENABLED" createdDate="2024-01-01 00:00:00" lastModifiedDate="2024-01-01 00:00:00"/>
    <PartyGroup partyId="UOC_MEDICINA_DEA" groupName="UOC Medicina DEA e Complessità Clinica" groupNameLocal="UOC Medicina DEA e Complessità Clinica" partyTypeId="PARTY_GROUP" />
    <PartyRole partyId="UOC_MEDICINA_DEA" roleTypeId="INTERNAL_ORGANIZATIO" fromDate="2024-01-01 00:00:00"/>
    <PartyRelationship partyIdFrom="DEPT_MEDICINA_INT" partyIdTo="UOC_MEDICINA_DEA" roleTypeIdFrom="INTERNAL_ORGANIZATIO" roleTypeIdTo="INTERNAL_ORGANIZATIO" partyRelationshipTypeId="GROUP_ROLLUP" fromDate="2024-01-01 00:00:00"/>
    
    <!-- UOC Endocrinologia -->
    <Party partyId="UOC_ENDOCRINOLOGIA" partyTypeId="PARTY_GROUP" statusId="PARTY_ENABLED" createdDate="2024-01-01 00:00:00" lastModifiedDate="2024-01-01 00:00:00"/>
    <PartyGroup partyId="UOC_ENDOCRINOLOGIA" groupName="UOC Endocrinologia" groupNameLocal="UOC Endocrinologia" partyTypeId="PARTY_GROUP" />
    <PartyRole partyId="UOC_ENDOCRINOLOGIA" roleTypeId="INTERNAL_ORGANIZATIO" fromDate="2024-01-01 00:00:00"/>
    <PartyRelationship partyIdFrom="DEPT_MEDICINA_INT" partyIdTo="UOC_ENDOCRINOLOGIA" roleTypeIdFrom="INTERNAL_ORGANIZATIO" roleTypeIdTo="INTERNAL_ORGANIZATIO" partyRelationshipTypeId="GROUP_ROLLUP" fromDate="2024-01-01 00:00:00"/>
    
    <!-- UOC Gastroenterologia -->
    <Party partyId="UOC_GASTROENTERO" partyTypeId="PARTY_GROUP" statusId="PARTY_ENABLED" createdDate="2024-01-01 00:00:00" lastModifiedDate="2024-01-01 00:00:00"/>
    <PartyGroup partyId="UOC_GASTROENTERO" groupName="UOC Gastroenterologia" groupNameLocal="UOC Gastroenterologia" partyTypeId="PARTY_GROUP" />
    <PartyRole partyId="UOC_GASTROENTERO" roleTypeId="INTERNAL_ORGANIZATIO" fromDate="2024-01-01 00:00:00"/>
    <PartyRelationship partyIdFrom="DEPT_MEDICINA_INT" partyIdTo="UOC_GASTROENTERO" roleTypeIdFrom="INTERNAL_ORGANIZATIO" roleTypeIdTo="INTERNAL_ORGANIZATIO" partyRelationshipTypeId="GROUP_ROLLUP" fromDate="2024-01-01 00:00:00"/>
    
    <!-- UOC Nefrologia -->
    <Party partyId="UOC_NEFROLOGIA" partyTypeId="PARTY_GROUP" statusId="PARTY_ENABLED" createdDate="2024-01-01 00:00:00" lastModifiedDate="2024-01-01 00:00:00"/>
    <PartyGroup partyId="UOC_NEFROLOGIA" groupName="UOC Nefrologia con Emodialisi" groupNameLocal="UOC Nefrologia con Emodialisi" partyTypeId="PARTY_GROUP" />
    <PartyRole partyId="UOC_NEFROLOGIA" roleTypeId="INTERNAL_ORGANIZATIO" fromDate="2024-01-01 00:00:00"/>
    <PartyRelationship partyIdFrom="DEPT_MEDICINA_INT" partyIdTo="UOC_NEFROLOGIA" roleTypeIdFrom="INTERNAL_ORGANIZATIO" roleTypeIdTo="INTERNAL_ORGANIZATIO" partyRelationshipTypeId="GROUP_ROLLUP" fromDate="2024-01-01 00:00:00"/>
    
    <!-- UOC Oncologia -->
    <Party partyId="UOC_ONCOLOGIA" partyTypeId="PARTY_GROUP" statusId="PARTY_ENABLED" createdDate="2024-01-01 00:00:00" lastModifiedDate="2024-01-01 00:00:00"/>
    <PartyGroup partyId="UOC_ONCOLOGIA" groupName="UOC Oncologia" groupNameLocal="UOC Oncologia" partyTypeId="PARTY_GROUP" />
    <PartyRole partyId="UOC_ONCOLOGIA" roleTypeId="INTERNAL_ORGANIZATIO" fromDate="2024-01-01 00:00:00"/>
    <PartyRelationship partyIdFrom="DEPT_MEDICINA_INT" partyIdTo="UOC_ONCOLOGIA" roleTypeIdFrom="INTERNAL_ORGANIZATIO" roleTypeIdTo="INTERNAL_ORGANIZATIO" partyRelationshipTypeId="GROUP_ROLLUP" fromDate="2024-01-01 00:00:00"/>
    
    <!-- UOC Pneumologia -->
    <Party partyId="UOC_PNEUMOLOGIA" partyTypeId="PARTY_GROUP" statusId="PARTY_ENABLED" createdDate="2024-01-01 00:00:00" lastModifiedDate="2024-01-01 00:00:00"/>
    <PartyGroup partyId="UOC_PNEUMOLOGIA" groupName="UOC Pneumologia" groupNameLocal="UOC Pneumologia" partyTypeId="PARTY_GROUP" />
    <PartyRole partyId="UOC_PNEUMOLOGIA" roleTypeId="INTERNAL_ORGANIZATIO" fromDate="2024-01-01 00:00:00"/>
    <PartyRelationship partyIdFrom="DEPT_MEDICINA_INT" partyIdTo="UOC_PNEUMOLOGIA" roleTypeIdFrom="INTERNAL_ORGANIZATIO" roleTypeIdTo="INTERNAL_ORGANIZATIO" partyRelationshipTypeId="GROUP_ROLLUP" fromDate="2024-01-01 00:00:00"/>
    
    <!-- UOC DEL DIPARTIMENTO DIAGNOSTICA -->
    
    <!-- UOC Anatomia Patologica -->
    <Party partyId="UOC_ANATOMIA_PATOL" partyTypeId="PARTY_GROUP" statusId="PARTY_ENABLED" createdDate="2024-01-01 00:00:00" lastModifiedDate="2024-01-01 00:00:00"/>
    <PartyGroup partyId="UOC_ANATOMIA_PATOL" groupName="UOC Anatomia Patologica" groupNameLocal="UOC Anatomia Patologica" partyTypeId="PARTY_GROUP" />
    <PartyRole partyId="UOC_ANATOMIA_PATOL" roleTypeId="INTERNAL_ORGANIZATIO" fromDate="2024-01-01 00:00:00"/>
    <PartyRelationship partyIdFrom="DEPT_DIAGNOSTICA" partyIdTo="UOC_ANATOMIA_PATOL" roleTypeIdFrom="INTERNAL_ORGANIZATIO" roleTypeIdTo="INTERNAL_ORGANIZATIO" partyRelationshipTypeId="GROUP_ROLLUP" fromDate="2024-01-01 00:00:00"/>
    
    <!-- UOC Radiologia Generale -->
    <Party partyId="UOC_RADIOLOGIA_GEN" partyTypeId="PARTY_GROUP" statusId="PARTY_ENABLED" createdDate="2024-01-01 00:00:00" lastModifiedDate="2024-01-01 00:00:00"/>
    <PartyGroup partyId="UOC_RADIOLOGIA_GEN" groupName="UOC Radiologia Generale e di Pronto Soccorso" groupNameLocal="UOC Radiologia Generale e di Pronto Soccorso" partyTypeId="PARTY_GROUP" />
    <PartyRole partyId="UOC_RADIOLOGIA_GEN" roleTypeId="INTERNAL_ORGANIZATIO" fromDate="2024-01-01 00:00:00"/>
    <PartyRelationship partyIdFrom="DEPT_DIAGNOSTICA" partyIdTo="UOC_RADIOLOGIA_GEN" roleTypeIdFrom="INTERNAL_ORGANIZATIO" roleTypeIdTo="INTERNAL_ORGANIZATIO" partyRelationshipTypeId="GROUP_ROLLUP" fromDate="2024-01-01 00:00:00"/>
    
    <!-- UOC Radiologia Vascolare -->
    <Party partyId="UOC_RADIOLOGIA_VASC" partyTypeId="PARTY_GROUP" statusId="PARTY_ENABLED" createdDate="2024-01-01 00:00:00" lastModifiedDate="2024-01-01 00:00:00"/>
    <PartyGroup partyId="UOC_RADIOLOGIA_VASC" groupName="UOC Radiologia Vascolare ed Interventistica" groupNameLocal="UOC Radiologia Vascolare ed Interventistica" partyTypeId="PARTY_GROUP" />
    <PartyRole partyId="UOC_RADIOLOGIA_VASC" roleTypeId="INTERNAL_ORGANIZATIO" fromDate="2024-01-01 00:00:00"/>
    <PartyRelationship partyIdFrom="DEPT_DIAGNOSTICA" partyIdTo="UOC_RADIOLOGIA_VASC" roleTypeIdFrom="INTERNAL_ORGANIZATIO" roleTypeIdTo="INTERNAL_ORGANIZATIO" partyRelationshipTypeId="GROUP_ROLLUP" fromDate="2024-01-01 00:00:00"/>
    
    <!-- UOC Medicina Nucleare -->
    <Party partyId="UOC_MEDICINA_NUCL" partyTypeId="PARTY_GROUP" statusId="PARTY_ENABLED" createdDate="2024-01-01 00:00:00" lastModifiedDate="2024-01-01 00:00:00"/>
    <PartyGroup partyId="UOC_MEDICINA_NUCL" groupName="UOC Medicina Nucleare" groupNameLocal="UOC Medicina Nucleare" partyTypeId="PARTY_GROUP" />
    <PartyRole partyId="UOC_MEDICINA_NUCL" roleTypeId="INTERNAL_ORGANIZATIO" fromDate="2024-01-01 00:00:00"/>
    <PartyRelationship partyIdFrom="DEPT_DIAGNOSTICA" partyIdTo="UOC_MEDICINA_NUCL" roleTypeIdFrom="INTERNAL_ORGANIZATIO" roleTypeIdTo="INTERNAL_ORGANIZATIO" partyRelationshipTypeId="GROUP_ROLLUP" fromDate="2024-01-01 00:00:00"/>
    
    <!-- UOC Patologia Clinica -->
    <Party partyId="UOC_PATOLOGIA_CLIN" partyTypeId="PARTY_GROUP" statusId="PARTY_ENABLED" createdDate="2024-01-01 00:00:00" lastModifiedDate="2024-01-01 00:00:00"/>
    <PartyGroup partyId="UOC_PATOLOGIA_CLIN" groupName="UOC Patologia Clinica" groupNameLocal="UOC Patologia Clinica" partyTypeId="PARTY_GROUP" />
    <PartyRole partyId="UOC_PATOLOGIA_CLIN" roleTypeId="INTERNAL_ORGANIZATIO" fromDate="2024-01-01 00:00:00"/>
    <PartyRelationship partyIdFrom="DEPT_DIAGNOSTICA" partyIdTo="UOC_PATOLOGIA_CLIN" roleTypeIdFrom="INTERNAL_ORGANIZATIO" roleTypeIdTo="INTERNAL_ORGANIZATIO" partyRelationshipTypeId="GROUP_ROLLUP" fromDate="2024-01-01 00:00:00"/>
    
    <!-- UOC DEL DIPARTIMENTO TERAPIE INTENSIVE -->
    
    <!-- UOC Rianimazione DEA -->
    <Party partyId="UOC_RIANIMAZIONE" partyTypeId="PARTY_GROUP" statusId="PARTY_ENABLED" createdDate="2024-01-01 00:00:00" lastModifiedDate="2024-01-01 00:00:00"/>
    <PartyGroup partyId="UOC_RIANIMAZIONE" groupName="UOC Rianimazione DEA" groupNameLocal="UOC Rianimazione DEA" partyTypeId="PARTY_GROUP" />
    <PartyRole partyId="UOC_RIANIMAZIONE" roleTypeId="INTERNAL_ORGANIZATIO" fromDate="2024-01-01 00:00:00"/>
    <PartyRelationship partyIdFrom="DEPT_TERAPIE_INT" partyIdTo="UOC_RIANIMAZIONE" roleTypeIdFrom="INTERNAL_ORGANIZATIO" roleTypeIdTo="INTERNAL_ORGANIZATIO" partyRelationshipTypeId="GROUP_ROLLUP" fromDate="2024-01-01 00:00:00"/>
    
    <!-- UOC Terapia Intensiva Post-Operatoria -->
    <Party partyId="UOC_TI_POST_OP" partyTypeId="PARTY_GROUP" statusId="PARTY_ENABLED" createdDate="2024-01-01 00:00:00" lastModifiedDate="2024-01-01 00:00:00"/>
    <PartyGroup partyId="UOC_TI_POST_OP" groupName="UOC Terapia Intensiva Post-Operatoria" groupNameLocal="UOC Terapia Intensiva Post-Operatoria" partyTypeId="PARTY_GROUP" />
    <PartyRole partyId="UOC_TI_POST_OP" roleTypeId="INTERNAL_ORGANIZATIO" fromDate="2024-01-01 00:00:00"/>
    <PartyRelationship partyIdFrom="DEPT_TERAPIE_INT" partyIdTo="UOC_TI_POST_OP" roleTypeIdFrom="INTERNAL_ORGANIZATIO" roleTypeIdTo="INTERNAL_ORGANIZATIO" partyRelationshipTypeId="GROUP_ROLLUP" fromDate="2024-01-01 00:00:00"/>
    
    <!-- UOC Terapia Intensiva Fegato -->
    <Party partyId="UOC_UTIF" partyTypeId="PARTY_GROUP" statusId="PARTY_ENABLED" createdDate="2024-01-01 00:00:00" lastModifiedDate="2024-01-01 00:00:00"/>
    <PartyGroup partyId="UOC_UTIF" groupName="UOC Terapia Intensiva Fegato (UTIF)" groupNameLocal="UOC Terapia Intensiva Fegato (UTIF)" partyTypeId="PARTY_GROUP" />
    <PartyRole partyId="UOC_UTIF" roleTypeId="INTERNAL_ORGANIZATIO" fromDate="2024-01-01 00:00:00"/>
    <PartyRelationship partyIdFrom="DEPT_TERAPIE_INT" partyIdTo="UOC_UTIF" roleTypeIdFrom="INTERNAL_ORGANIZATIO" roleTypeIdTo="INTERNAL_ORGANIZATIO" partyRelationshipTypeId="GROUP_ROLLUP" fromDate="2024-01-01 00:00:00"/>
    
    <!-- UOC Terapia Intensiva Grandi Ustionati -->
    <Party partyId="10059" partyTypeId="PARTY_GROUP" statusId="PARTY_ENABLED" createdDate="2024-01-01 00:00:00" lastModifiedDate="2024-01-01 00:00:00"/>
    <PartyGroup partyId="10059" groupName="UOC Terapia Intensiva Grandi Ustionati (TIGU)" groupNameLocal="UOC Terapia Intensiva Grandi Ustionati (TIGU)" partyTypeId="PARTY_GROUP" />
    <PartyRole partyId="10059" roleTypeId="INTERNAL_ORGANIZATIO" fromDate="2024-01-01 00:00:00"/>
    <PartyRelationship partyIdFrom="DEPT_TERAPIE_INT" partyIdTo="10059" roleTypeIdFrom="INTERNAL_ORGANIZATIO" roleTypeIdTo="INTERNAL_ORGANIZATIO" partyRelationshipTypeId="GROUP_ROLLUP" fromDate="2024-01-01 00:00:00"/>
    
    <!-- UOC DEL DIPARTIMENTO SERVIZI AMMINISTRATIVI -->
    
    <!-- UOC Gestione Risorse Umane -->
    <Party partyId="UOC_GRU" partyTypeId="PARTY_GROUP" statusId="PARTY_ENABLED" createdDate="2024-01-01 00:00:00" lastModifiedDate="2024-01-01 00:00:00"/>
    <PartyGroup partyId="UOC_GRU" groupName="UOC Gestione Risorse Umane (GRU)" groupNameLocal="UOC Gestione Risorse Umane (GRU)" partyTypeId="PARTY_GROUP" />
    <PartyRole partyId="UOC_GRU" roleTypeId="INTERNAL_ORGANIZATIO" fromDate="2024-01-01 00:00:00"/>
    <PartyRelationship partyIdFrom="DEPT_AMMINISTRATIVO" partyIdTo="UOC_GRU" roleTypeIdFrom="INTERNAL_ORGANIZATIO" roleTypeIdTo="INTERNAL_ORGANIZATIO" partyRelationshipTypeId="GROUP_ROLLUP" fromDate="2024-01-01 00:00:00"/>
    
    <!-- UOC Gestione Economica e Finanziaria -->
    <Party partyId="UOC_GEF" partyTypeId="PARTY_GROUP" statusId="PARTY_ENABLED" createdDate="2024-01-01 00:00:00" lastModifiedDate="2024-01-01 00:00:00"/>
    <PartyGroup partyId="UOC_GEF" groupName="UOC Gestione Economica e Finanziaria (GEF)" groupNameLocal="UOC Gestione Economica e Finanziaria (GEF)" partyTypeId="PARTY_GROUP" />
    <PartyRole partyId="UOC_GEF" roleTypeId="INTERNAL_ORGANIZATIO" fromDate="2024-01-01 00:00:00"/>
    <PartyRelationship partyIdFrom="DEPT_AMMINISTRATIVO" partyIdTo="UOC_GEF" roleTypeIdFrom="INTERNAL_ORGANIZATIO" roleTypeIdTo="INTERNAL_ORGANIZATIO" partyRelationshipTypeId="GROUP_ROLLUP" fromDate="2024-01-01 00:00:00"/>
    
    <!-- UOC Affari Generali -->
    <Party partyId="UOC_AFFARI_GEN" partyTypeId="PARTY_GROUP" statusId="PARTY_ENABLED" createdDate="2024-01-01 00:00:00" lastModifiedDate="2024-01-01 00:00:00"/>
    <PartyGroup partyId="UOC_AFFARI_GEN" groupName="UOC Affari Generali" groupNameLocal="UOC Affari Generali" partyTypeId="PARTY_GROUP" />
    <PartyRole partyId="UOC_AFFARI_GEN" roleTypeId="INTERNAL_ORGANIZATIO" fromDate="2024-01-01 00:00:00"/>
    <PartyRelationship partyIdFrom="DEPT_AMMINISTRATIVO" partyIdTo="UOC_AFFARI_GEN" roleTypeIdFrom="INTERNAL_ORGANIZATIO" roleTypeIdTo="INTERNAL_ORGANIZATIO" partyRelationshipTypeId="GROUP_ROLLUP" fromDate="2024-01-01 00:00:00"/>
    
    <!-- UOC Provveditorato ed Economato -->
    <Party partyId="UOC_PROVVEDITORATO" partyTypeId="PARTY_GROUP" statusId="PARTY_ENABLED" createdDate="2024-01-01 00:00:00" lastModifiedDate="2024-01-01 00:00:00"/>
    <PartyGroup partyId="UOC_PROVVEDITORATO" groupName="UOC Provveditorato ed Economato" groupNameLocal="UOC Provveditorato ed Economato" partyTypeId="PARTY_GROUP" />
    <PartyRole partyId="UOC_PROVVEDITORATO" roleTypeId="INTERNAL_ORGANIZATIO" fromDate="2024-01-01 00:00:00"/>
    <PartyRelationship partyIdFrom="DEPT_AMMINISTRATIVO" partyIdTo="UOC_PROVVEDITORATO" roleTypeIdFrom="INTERNAL_ORGANIZATIO" roleTypeIdTo="INTERNAL_ORGANIZATIO" partyRelationshipTypeId="GROUP_ROLLUP" fromDate="2024-01-01 00:00:00"/>
    
    <!-- DIRIGENTI E DIPENDENTI OSPEDALE CARDARELLI -->
    
    <!-- DIRIGENTI DIPARTIMENTO CARDIO-TORACO-VASCOLARE -->
    
    <!-- Direttore Dipartimento Cardio-Toraco-Vascolare -->
    <Party partyId="DIR_DEPT_CAR_TOR" partyTypeId="PERSON" statusId="PARTY_ENABLED" createdDate="2024-01-01 00:00:00" lastModifiedDate="2024-01-01 00:00:00"/>
    <Person partyId="DIR_DEPT_CAR_TOR" firstName="Alessandro" lastName="Cardiotoraco" personalTitle="Dr."/>
    <PartyRole partyId="DIR_DEPT_CAR_TOR" roleTypeId="DEPARTMENT_MANAGER" fromDate="2024-01-01 00:00:00"/>
    <PartyRelationship partyIdFrom="DIR_DEPT_CAR_TOR" partyIdTo="DEPT_CAR_TOR" roleTypeIdFrom="DEPARTMENT_MANAGER" roleTypeIdTo="INTERNAL_ORGANIZATIO" partyRelationshipTypeId="RESPONSIBLE_FOR" fromDate="2024-01-01 00:00:00"/>
    
    <!-- Dirigente UOC Cardiologia -->
    <Party partyId="DIR_CARDIOLOGIA" partyTypeId="PERSON" statusId="PARTY_ENABLED" createdDate="2024-01-01 00:00:00" lastModifiedDate="2024-01-01 00:00:00"/>
    <Person partyId="DIR_CARDIOLOGIA" firstName="Francesco" lastName="Cardio" personalTitle="Dr."/>
    <PartyRole partyId="DIR_CARDIOLOGIA" roleTypeId="DEPARTMENT_MANAGER" fromDate="2024-01-01 00:00:00"/>
    <PartyRelationship partyIdFrom="DIR_CARDIOLOGIA" partyIdTo="UOC_CARDIOLOGIA" roleTypeIdFrom="DEPARTMENT_MANAGER" roleTypeIdTo="INTERNAL_ORGANIZATIO" partyRelationshipTypeId="RESPONSIBLE_FOR" fromDate="2024-01-01 00:00:00"/>
    
    <!-- Dirigente UOC Cardiologia con UTIC -->
    <Party partyId="DIR_CARDIOLOGIA_UTIC" partyTypeId="PERSON" statusId="PARTY_ENABLED" createdDate="2024-01-01 00:00:00" lastModifiedDate="2024-01-01 00:00:00"/>
    <Person partyId="DIR_CARDIOLOGIA_UTIC" firstName="Marco" lastName="Uticelli" personalTitle="Dr."/>
    <PartyRole partyId="DIR_CARDIOLOGIA_UTIC" roleTypeId="DEPARTMENT_MANAGER" fromDate="2024-01-01 00:00:00"/>
    <PartyRelationship partyIdFrom="DIR_CARDIOLOGIA_UTIC" partyIdTo="UOC_CARDIOLOGIA_UTIC" roleTypeIdFrom="DEPARTMENT_MANAGER" roleTypeIdTo="INTERNAL_ORGANIZATIO" partyRelationshipTypeId="RESPONSIBLE_FOR" fromDate="2024-01-01 00:00:00"/>
    
    <!-- Dirigente UOC Chirurgia Toracica -->
    <Party partyId="DIR_CHIR_TORACICA" partyTypeId="PERSON" statusId="PARTY_ENABLED" createdDate="2024-01-01 00:00:00" lastModifiedDate="2024-01-01 00:00:00"/>
    <Person partyId="DIR_CHIR_TORACICA" firstName="Roberto" lastName="Toracico" personalTitle="Prof."/>
    <PartyRole partyId="DIR_CHIR_TORACICA" roleTypeId="DEPARTMENT_MANAGER" fromDate="2024-01-01 00:00:00"/>
    <PartyRelationship partyIdFrom="DIR_CHIR_TORACICA" partyIdTo="UOC_CHIR_TORACICA" roleTypeIdFrom="DEPARTMENT_MANAGER" roleTypeIdTo="INTERNAL_ORGANIZATIO" partyRelationshipTypeId="RESPONSIBLE_FOR" fromDate="2024-01-01 00:00:00"/>
    
    <!-- DIPENDENTI UOC CARDIOLOGIA -->
    
    <!-- Giuseppe Verdi - Dipendente UOC Cardiologia -->
    <Party partyId="10071" partyTypeId="PERSON" statusId="PARTY_ENABLED" createdDate="2024-01-01 00:00:00" lastModifiedDate="2024-01-01 00:00:00"/>
    <Person partyId="10071" firstName="Giuseppe" lastName="Verdi" personalTitle="Dr."/>
    <PartyRole partyId="10071" roleTypeId="EMPLOYEE" fromDate="2024-01-01 00:00:00"/>
    <PartyRelationship partyIdFrom="10071" partyIdTo="UOC_CARDIOLOGIA" roleTypeIdFrom="EMPLOYEE" roleTypeIdTo="INTERNAL_ORGANIZATIO" partyRelationshipTypeId="EMPLOYMENT" fromDate="2024-01-01 00:00:00"/>
    
    <!-- Maria Cuore - Dipendente UOC Cardiologia -->
    <Party partyId="10072" partyTypeId="PERSON" statusId="PARTY_ENABLED" createdDate="2024-01-01 00:00:00" lastModifiedDate="2024-01-01 00:00:00"/>
    <Person partyId="10072" firstName="Maria" lastName="Cuore" personalTitle="Dr.ssa"/>
    <PartyRole partyId="10072" roleTypeId="EMPLOYEE" fromDate="2024-01-01 00:00:00"/>
    <PartyRelationship partyIdFrom="10072" partyIdTo="UOC_CARDIOLOGIA" roleTypeIdFrom="EMPLOYEE" roleTypeIdTo="INTERNAL_ORGANIZATIO" partyRelationshipTypeId="EMPLOYMENT" fromDate="2024-01-01 00:00:00"/>
    
    <!-- Anna Semplice - Dipendente UOC Cardiologia -->
    <Party partyId="11073" partyTypeId="PERSON" statusId="PARTY_ENABLED" createdDate="2024-01-01 00:00:00" lastModifiedDate="2024-01-01 00:00:00"/>
    <Person partyId="11073" firstName="Anna" lastName="Semplice" personalTitle="Dr.ssa"/>
    <PartyRole partyId="11073" roleTypeId="EMPLOYEE" fromDate="2024-01-01 00:00:00"/>
    <PartyRelationship partyIdFrom="11073" partyIdTo="UOC_CARDIOLOGIA" roleTypeIdFrom="EMPLOYEE" roleTypeIdTo="INTERNAL_ORGANIZATIO" partyRelationshipTypeId="EMPLOYMENT" fromDate="2024-01-01 00:00:00"/>
    
    <!-- DIPENDENTI UOC ORTOPEDIA 1 -->
    
    <!-- Luca Osso - Dipendente UOC Ortopedia 1 -->
    <Party partyId="10074" partyTypeId="PERSON" statusId="PARTY_ENABLED" createdDate="2024-01-01 00:00:00" lastModifiedDate="2024-01-01 00:00:00"/>
    <Person partyId="10074" firstName="Luca" lastName="Osso" personalTitle="Dr."/>
    <PartyRole partyId="10074" roleTypeId="EMPLOYEE" fromDate="2024-01-01 00:00:00"/>
    <PartyRelationship partyIdFrom="10074" partyIdTo="UOC_ORTOPEDIA_1" roleTypeIdFrom="EMPLOYEE" roleTypeIdTo="INTERNAL_ORGANIZATIO" partyRelationshipTypeId="EMPLOYMENT" fromDate="2024-01-01 00:00:00"/>
    
    <!-- DIRIGENTI DIPARTIMENTO CHIRURGICO -->
    
    <!-- Direttore Dipartimento Chirurgico -->
    <Party partyId="DIR_DEPT_CHIRURGICO" partyTypeId="PERSON" statusId="PARTY_ENABLED" createdDate="2024-01-01 00:00:00" lastModifiedDate="2024-01-01 00:00:00"/>
    <Person partyId="DIR_DEPT_CHIRURGICO" firstName="Luigi" lastName="Bisturi" personalTitle="Prof."/>
    <PartyRole partyId="DIR_DEPT_CHIRURGICO" roleTypeId="DEPARTMENT_MANAGER" fromDate="2024-01-01 00:00:00"/>
    <PartyRelationship partyIdFrom="DIR_DEPT_CHIRURGICO" partyIdTo="DEPT_CHIRURGICO" roleTypeIdFrom="DEPARTMENT_MANAGER" roleTypeIdTo="INTERNAL_ORGANIZATIO" partyRelationshipTypeId="RESPONSIBLE_FOR" fromDate="2024-01-01 00:00:00"/>
    
    <!-- Dirigente UOC Chirurgia Generale Gastroenterologica -->
    <Party partyId="DIR_CHIR_GASTRO" partyTypeId="PERSON" statusId="PARTY_ENABLED" createdDate="2024-01-01 00:00:00" lastModifiedDate="2024-01-01 00:00:00"/>
    <Person partyId="DIR_CHIR_GASTRO" firstName="Paolo" lastName="Gastricelli" personalTitle="Dr."/>
    <PartyRole partyId="DIR_CHIR_GASTRO" roleTypeId="DEPARTMENT_MANAGER" fromDate="2024-01-01 00:00:00"/>
    <PartyRelationship partyIdFrom="DIR_CHIR_GASTRO" partyIdTo="UOC_CHIR_GASTRO" roleTypeIdFrom="DEPARTMENT_MANAGER" roleTypeIdTo="INTERNAL_ORGANIZATIO" partyRelationshipTypeId="RESPONSIBLE_FOR" fromDate="2024-01-01 00:00:00"/>
    
    <!-- Dirigente UOC Ortopedia 1 -->
    <Party partyId="DIR_ORTOPEDIA_1" partyTypeId="PERSON" statusId="PARTY_ENABLED" createdDate="2024-01-01 00:00:00" lastModifiedDate="2024-01-01 00:00:00"/>
    <Person partyId="DIR_ORTOPEDIA_1" firstName="Stefano" lastName="Ossetti" personalTitle="Dr."/>
    <PartyRole partyId="DIR_ORTOPEDIA_1" roleTypeId="DEPARTMENT_MANAGER" fromDate="2024-01-01 00:00:00"/>
    <PartyRelationship partyIdFrom="DIR_ORTOPEDIA_1" partyIdTo="UOC_ORTOPEDIA_1" roleTypeIdFrom="DEPARTMENT_MANAGER" roleTypeIdTo="INTERNAL_ORGANIZATIO" partyRelationshipTypeId="RESPONSIBLE_FOR" fromDate="2024-01-01 00:00:00"/>
    
    <!-- DIRIGENTI DIPARTIMENTO MEDICINA INTERNA -->
    
    <!-- Direttore Dipartimento Medicina Interna -->
    <Party partyId="DIR_DEPT_MEDICINA_INT" partyTypeId="PERSON" statusId="PARTY_ENABLED" createdDate="2024-01-01 00:00:00" lastModifiedDate="2024-01-01 00:00:00"/>
    <Person partyId="DIR_DEPT_MEDICINA_INT" firstName="Giovanni" lastName="Internista" personalTitle="Prof."/>
    <PartyRole partyId="DIR_DEPT_MEDICINA_INT" roleTypeId="DEPARTMENT_MANAGER" fromDate="2024-01-01 00:00:00"/>
    <PartyRelationship partyIdFrom="DIR_DEPT_MEDICINA_INT" partyIdTo="DEPT_MEDICINA_INT" roleTypeIdFrom="DEPARTMENT_MANAGER" roleTypeIdTo="INTERNAL_ORGANIZATIO" partyRelationshipTypeId="RESPONSIBLE_FOR" fromDate="2024-01-01 00:00:00"/>
    
</entity-engine-xml>
